odoo/addons/website_sale_product_publish_date/README.rst
odoo/addons/website_sale_product_publish_date/__init__.py
odoo/addons/website_sale_product_publish_date/__manifest__.py
odoo/addons/website_sale_product_publish_date/i18n/website_sale_product_publish_date.pot
odoo/addons/website_sale_product_publish_date/models/__init__.py
odoo/addons/website_sale_product_publish_date/models/product_template.py
odoo/addons/website_sale_product_publish_date/readme/CONTRIBUTOR.rst
odoo/addons/website_sale_product_publish_date/readme/DESCRIPTION.rst
odoo/addons/website_sale_product_publish_date/static/description/icon.png
odoo/addons/website_sale_product_publish_date/static/description/index.html
odoo/addons/website_sale_product_publish_date/tests/__init__.py
odoo/addons/website_sale_product_publish_date/tests/test_website_sale_product_publish_date.py
odoo/addons/website_sale_product_publish_date/views/product_template_views.xml
odoo_addon_website_sale_product_publish_date-15.0.1.0.0.3.dist-info/METADATA
odoo_addon_website_sale_product_publish_date-15.0.1.0.0.3.dist-info/WHEEL
odoo_addon_website_sale_product_publish_date-15.0.1.0.0.3.dist-info/top_level.txt
odoo_addon_website_sale_product_publish_date-15.0.1.0.0.3.dist-info/RECORD
